swarmauri_signing_ca/CASigner.py
swarmauri_signing_ca/__init__.py
swarmauri_signing_ca-0.3.0.dev4.dist-info/LICENSE
swarmauri_signing_ca-0.3.0.dev4.dist-info/METADATA
swarmauri_signing_ca-0.3.0.dev4.dist-info/WHEEL
swarmauri_signing_ca-0.3.0.dev4.dist-info/entry_points.txt
swarmauri_signing_ca-0.3.0.dev4.dist-info/RECORD
